NDI_communication/__init__.py
NDI_Communication-0.0.1.dist-info/METADATA
NDI_Communication-0.0.1.dist-info/WHEEL
NDI_Communication-0.0.1.dist-info/top_level.txt
NDI_Communication-0.0.1.dist-info/RECORD
